cli/__init__.py
cli/main.py
cli/commands/__init__.py
cli/commands/generate_key.py
cli/commands/make.py
cli/commands/setup.py
cli/commands/start.py
cli/commands/make_context/__init__.py
cli/commands/make_context/api_context.py
cli/commands/make_context/llms_context.py
cli/commands/make_context/prompts_context.py
cli/commands/make_context/tools_context.py
bafcode-1.1.6.dist-info/METADATA
bafcode-1.1.6.dist-info/WHEEL
bafcode-1.1.6.dist-info/entry_points.txt
bafcode-1.1.6.dist-info/top_level.txt
bafcode-1.1.6.dist-info/RECORD
