Metadata-Version: 2.1
Name: bafcode
Version: 1.1.6
Summary: BafCode Framework CLI
Home-page: https://github.com/aitelabranding/bafcode_cli
Author: Imad Ait El Arabi
Author-email: business@aitelabranding.com
Classifier: Programming Language :: Python :: 3
Classifier: License :: OSI Approved :: MIT License
Requires-Dist: cryptography
Requires-Dist: requests
Requires-Dist: Flask
Requires-Dist: python-dotenv
Requires-Dist: openai
